pyencrypt/__init__.py
pyencrypt/aes.py
pyencrypt/cli.py
pyencrypt/decrypt.py
pyencrypt/encrypt.py
pyencrypt/generate.py
pyencrypt/license.py
pyencrypt/loader.py
pyencrypt/ntt.py
pyencrypt_pye-0.5.0.dist-info/LICENSE
pyencrypt_pye-0.5.0.dist-info/METADATA
pyencrypt_pye-0.5.0.dist-info/WHEEL
pyencrypt_pye-0.5.0.dist-info/entry_points.txt
pyencrypt_pye-0.5.0.dist-info/top_level.txt
pyencrypt_pye-0.5.0.dist-info/RECORD
