Metadata-Version: 2.1
Name: pyencrypt-pye
Version: 0.5.0
Summary: Encrypt python source code and import module dynamically.
Home-page: https://github.com/ZhaoQi99/pyencrypt-pye
Author: Qi Zhao
Author-email: zhaoqi99@outlook.com
License: UNKNOWN
Project-URL: Homepage, https://github.com/ZhaoQi99/pyencrypt-pye
Project-URL: Changelog, https://github.com/ZhaoQi99/pyencrypt-pye/releases
Project-URL: Source, https://github.com/ZhaoQi99/pyencrypt-pye
Project-URL: Issue Tracker, https://github.com/ZhaoQi99/pyencrypt-pye/issues
Keywords: python-encrypt,import-hook
Platform: UNKNOWN
Classifier: License :: OSI Approved :: GNU General Public License v3 (GPLv3)
Classifier: Programming Language :: Python :: 3
Classifier: Programming Language :: Python :: 3.7
Classifier: Programming Language :: Python :: 3.8
Classifier: Programming Language :: Python :: 3.9
Classifier: Programming Language :: Python :: 3.10
Classifier: Programming Language :: Python :: 3.11
Classifier: Programming Language :: Python :: 3.12
Classifier: Programming Language :: Python :: 3.13
Classifier: Programming Language :: Python :: Implementation :: CPython
Classifier: Environment :: Console
Requires-Python: <3.14,>=3.6
License-File: LICENSE
Requires-Dist: Cython (>=0.29.30)
Requires-Dist: pycryptodome (>=3.14.1)
Requires-Dist: click (>=8.0.0)
Requires-Dist: setuptools (<=60.9.0) ; python_version < "3.12"
Requires-Dist: python-minifier (>=2.6.0) ; python_version < "3.14"
Requires-Dist: setuptools (>=66.1.0) ; python_version >= "3.12"
Provides-Extra: dev
Requires-Dist: isort ; extra == 'dev'
Requires-Dist: black ; extra == 'dev'
Requires-Dist: pytest ; extra == 'dev'
Requires-Dist: ipython ; extra == 'dev'
Requires-Dist: flake8 ; extra == 'dev'
